mau/__init__.py
mau/errors.py
mau/helpers.py
mau/main.py
mau/test_helpers.py
mau/environment/__init__.py
mau/environment/environment.py
mau/lexers/__init__.py
mau/lexers/arguments_lexer.py
mau/lexers/base_lexer.py
mau/lexers/main_lexer.py
mau/lexers/preprocess_variables_lexer.py
mau/lexers/text_lexer.py
mau/nodes/__init__.py
mau/nodes/arguments.py
mau/nodes/block.py
mau/nodes/content.py
mau/nodes/footnotes.py
mau/nodes/header.py
mau/nodes/inline.py
mau/nodes/lists.py
mau/nodes/macros.py
mau/nodes/nodes.py
mau/nodes/page.py
mau/nodes/paragraph.py
mau/nodes/source.py
mau/nodes/toc.py
mau/parsers/__init__.py
mau/parsers/arguments.py
mau/parsers/arguments_parser.py
mau/parsers/attributes.py
mau/parsers/base_parser.py
mau/parsers/footnotes.py
mau/parsers/internal_links.py
mau/parsers/main_parser.py
mau/parsers/preprocess_variables_parser.py
mau/parsers/text_parser.py
mau/parsers/toc.py
mau/text_buffer/__init__.py
mau/text_buffer/context.py
mau/text_buffer/text_buffer.py
mau/tokens/__init__.py
mau/tokens/tokens.py
mau/visitors/__init__.py
mau/visitors/base_visitor.py
mau/visitors/jinja_visitor.py
mau-4.0.1.dist-info/entry_points.txt
mau-4.0.1.dist-info/LICENSE
mau-4.0.1.dist-info/WHEEL
mau-4.0.1.dist-info/METADATA
mau-4.0.1.dist-info/RECORD
