Metadata-Version: 2.1
Name: mau
Version: 4.0.1
Summary: A lightweight template-driven markup language
Author-email: Leonardo Giordani <giordani.leonardo@gmail.com>
Requires-Python: >=3.7
Classifier: Development Status :: 5 - Production/Stable
Classifier: License :: OSI Approved :: MIT License
Classifier: Intended Audience :: Developers
Classifier: Operating System :: OS Independent
Classifier: Programming Language :: Python
Classifier: Programming Language :: Python :: 3
Classifier: Programming Language :: Python :: 3.7
Classifier: Programming Language :: Python :: 3.8
Classifier: Programming Language :: Python :: 3.9
Classifier: Programming Language :: Python :: 3.10
Classifier: Topic :: Software Development :: Libraries :: Python Modules
Requires-Dist: Jinja2
Requires-Dist: pyyaml
Requires-Dist: tabulate
Requires-Dist: mau[testing] ; extra == "development"
Requires-Dist: black ; extra == "development"
Requires-Dist: flake8 ; extra == "development"
Requires-Dist: flake8-pyproject ; extra == "development"
Requires-Dist: flit ; extra == "development"
Requires-Dist: isort ; extra == "development"
Requires-Dist: pip ; extra == "development"
Requires-Dist: pylint ; extra == "development"
Requires-Dist: wheel ; extra == "development"
Requires-Dist: coverage ; extra == "testing"
Requires-Dist: nox ; extra == "testing"
Requires-Dist: pytest ; extra == "testing"
Requires-Dist: pytest-cov ; extra == "testing"
Requires-Dist: pytest-icdiff ; extra == "testing"
Project-URL: Home, https://github.com/Project-Mau/mau
Provides-Extra: development
Provides-Extra: testing
